mikla/main.py
mikla/__init__.py
mikla-0.2.1.dist-info/entry_points.txt
mikla-0.2.1.dist-info/top_level.txt
mikla-0.2.1.dist-info/METADATA
mikla-0.2.1.dist-info/DESCRIPTION.rst
mikla-0.2.1.dist-info/metadata.json
mikla-0.2.1.dist-info/WHEEL
mikla-0.2.1.dist-info/RECORD
