Metadata-Version: 2.0
Name: mikla
Version: 0.2.1
Summary: A command line tool to edit text files encrypted with GnuPG whilst preventing the plaintext from being written to the hard drive.
Home-page: http://dirtymonkey.co.uk/mikla
Author: Matt Deacalion Stevens
Author-email: matt@dirtymonkey.co.uk
License: MIT
Keywords: encryption security gnupg gpg
Platform: UNKNOWN
Classifier: Development Status :: 4 - Beta
Classifier: Environment :: Console
Classifier: Intended Audience :: Developers
Classifier: Intended Audience :: End Users/Desktop
Classifier: License :: OSI Approved :: MIT License
Classifier: Natural Language :: English
Classifier: Operating System :: POSIX :: Linux
Classifier: Operating System :: POSIX :: BSD
Classifier: Programming Language :: Python :: 2.7
Classifier: Programming Language :: Python :: 3.2
Classifier: Programming Language :: Python :: 3.3
Classifier: Programming Language :: Python :: 3.4
Classifier: Topic :: Security :: Cryptography
Classifier: Topic :: Communications
Classifier: Topic :: Utilities
Requires-Dist: docopt (>=0.6.2)
